src/__init__.py
src/main.py
samcarswell_test-0.20.1.dist-info/METADATA
samcarswell_test-0.20.1.dist-info/WHEEL
samcarswell_test-0.20.1.dist-info/entry_points.txt
samcarswell_test-0.20.1.dist-info/top_level.txt
samcarswell_test-0.20.1.dist-info/RECORD
